flowco_streamlit_flow-0.0.2.dist-info/licenses/LICENSE
streamlit_flow/__init__.py
streamlit_flow/elements.py
streamlit_flow/layouts.py
streamlit_flow/state.py
streamlit_flow/frontend/build/asset-manifest.json
streamlit_flow/frontend/build/bootstrap.min.css
streamlit_flow/frontend/build/index.html
streamlit_flow/frontend/build/static/css/main.8b839d59.css
streamlit_flow/frontend/build/static/js/main.7dbd83fc.js
streamlit_flow/frontend/build/static/js/main.7dbd83fc.js.LICENSE.txt
streamlit_flow/frontend/build/static/media/KaTeX_AMS-Regular.73ea273a72f4aca30ca5.woff2
streamlit_flow/frontend/build/static/media/KaTeX_AMS-Regular.853be92419a6c3766b9a.ttf
streamlit_flow/frontend/build/static/media/KaTeX_AMS-Regular.d562e886c52f12660a41.woff
streamlit_flow/frontend/build/static/media/KaTeX_Caligraphic-Bold.7489a2fbfb9bfe704420.ttf
streamlit_flow/frontend/build/static/media/KaTeX_Caligraphic-Bold.a1abf90dfd72792a577a.woff2
streamlit_flow/frontend/build/static/media/KaTeX_Caligraphic-Bold.d757c535a2e5902f1325.woff
streamlit_flow/frontend/build/static/media/KaTeX_Caligraphic-Regular.7e873d3833eb108a0758.ttf
streamlit_flow/frontend/build/static/media/KaTeX_Caligraphic-Regular.d6484fce1ef428d5bd94.woff2
streamlit_flow/frontend/build/static/media/KaTeX_Caligraphic-Regular.db074fa22cf224af93d7.woff
streamlit_flow/frontend/build/static/media/KaTeX_Fraktur-Bold.354501bac435c3264834.woff
streamlit_flow/frontend/build/static/media/KaTeX_Fraktur-Bold.4c761b3711973ab04edf.ttf
streamlit_flow/frontend/build/static/media/KaTeX_Fraktur-Bold.931d67ea207ab37ee693.woff2
streamlit_flow/frontend/build/static/media/KaTeX_Fraktur-Regular.172d3529b26f8cedef6b.woff2
streamlit_flow/frontend/build/static/media/KaTeX_Fraktur-Regular.6fdf0ac577be0ba82a4c.woff
streamlit_flow/frontend/build/static/media/KaTeX_Fraktur-Regular.ed305b5434865e06ffde.ttf
streamlit_flow/frontend/build/static/media/KaTeX_Main-Bold.0c3b8929d377c0e9b2f3.woff
streamlit_flow/frontend/build/static/media/KaTeX_Main-Bold.39890742bc957b368704.woff2
flowco_streamlit_flow-0.0.2.dist-info/METADATA
flowco_streamlit_flow-0.0.2.dist-info/WHEEL
flowco_streamlit_flow-0.0.2.dist-info/top_level.txt
flowco_streamlit_flow-0.0.2.dist-info/RECORD
