Metadata-Version: 2.4
Name: flowco-streamlit-flow
Version: 0.0.2
Summary: Streamlit Component Wrapper for React Flow, modified for Flowco.  Original: https://github.com/dkapur17/streamlit-flow
Home-page: https://github.com/stephenfreund/flowco-streamlit-flow
Author: Stephen Freund
Author-email: sfreund@williams.edu
Requires-Python: >=3.8
License-File: LICENSE
Requires-Dist: streamlit>=1.0.0
Provides-Extra: devel
Requires-Dist: wheel; extra == "devel"
Requires-Dist: pytest==7.4.0; extra == "devel"
Requires-Dist: playwright==1.39.0; extra == "devel"
Requires-Dist: requests==2.31.0; extra == "devel"
Requires-Dist: pytest-playwright-snapshot==1.0; extra == "devel"
Requires-Dist: pytest-rerunfailures==12.0; extra == "devel"
Dynamic: author
Dynamic: author-email
Dynamic: description
Dynamic: description-content-type
Dynamic: home-page
Dynamic: license-file
Dynamic: provides-extra
Dynamic: requires-dist
Dynamic: requires-python
Dynamic: summary
